Workbook

Sheet Estoque
A1: CONTROLE DE ESTOQUE — ASSISTÊNCIA TÉCNICA DE INFORMÁTICA
A2: Atualizado em: 14/10/2026 | Preencha apenas as células de dados (linhas 5 em diante). Colunas com fórmula são calculadas automaticamente.
A3: Legenda: células em amarelo = exemplo de preenchimento • coluna Status calculada automaticamente a partir da Qtd. em Estoque x Estoque Mínimo • cole o link direto da imagem (ex: Google Drive, Imgur, site do fabricante) na coluna 'Link da Imagem'
A5: Código | B5: Categoria | C5: Produto / Peça | D5: Marca | E5: Modelo / Especificação | F5: Descrição | G5: Unidade | H5: Qtd. em Estoque | I5: Estoque Mínimo | J5: Estoque Máximo | K5: Preço de Custo (R$) | L5: Preço de Venda (R$) | M5: Margem (%) | N5: Valor Total em Estoque (R$) | O5: Fornecedor | P5: Localização (Prateleira) | Q5: Data de Entrada | R5: Status | S5: Link da Imagem do Produto | T5: Observações
A6: EST-001 | B6: Armazenamento | C6: SSD 240GB SATA III | D6: Kingston | E6: A400 240GB | F6: SSD 2.5'' SATA III, leitura até 500MB/s | G6: UN | H6: 18 | I6: 5 | J6: 30 | K6: 95 | L6: 169.9 | M6: =IFERROR((L6-K6)/K6,0) -> 0.78842105 | N6: =H6*K6 -> 1710 | O6: Kabum Distribuidora | P6: A1-01 | Q6: 03/09/2026 | R6: =IF(H6<=0,"SEM ESTOQUE",IF(H6<=I6,"ESTOQUE BAIXO","OK")) -> OK | S6: https://exemplo.com/imagens/ssd-kingston-a400-240gb.jpg | T6: Produto de saída rápida
A7: EST-002 | B7: Armazenamento | C7: SSD 480GB SATA III | D7: Kingston | E7: A400 480GB | F7: SSD 2.5'' SATA III, leitura até 500MB/s | G7: UN | H7: 12 | I7: 4 | J7: 20 | K7: 149 | L7: 259.9 | M7: =IFERROR((L7-K7)/K7,0) -> 0.7442953 | N7: =H7*K7 -> 1788 | O7: Kabum Distribuidora | P7: A1-02 | Q7: 03/09/2026 | R7: =IF(H7<=0,"SEM ESTOQUE",IF(H7<=I7,"ESTOQUE BAIXO","OK")) -> OK | S7: https://exemplo.com/imagens/ssd-kingston-a400-480gb.jpg
A8: EST-003 | B8: Armazenamento | C8: SSD NVMe 500GB M.2 | D8: WD | E8: Blue SN570 | F8: SSD NVMe PCIe Gen3 x4, leitura até 3500MB/s | G8: UN | H8: 9 | I8: 3 | J8: 15 | K8: 189 | L8: 329.9 | M8: =IFERROR((L8-K8)/K8,0) -> 0.74550265 | N8: =H8*K8 -> 1701 | O8: Western Digital Brasil | P8: A1-05 | Q8: 10/09/2026 | R8: =IF(H8<=0,"SEM ESTOQUE",IF(H8<=I8,"ESTOQUE BAIXO","OK")) -> OK | S8: https://exemplo.com/imagens/ssd-wd-sn570-500gb.jpg
A9: EST-004 | B9: Armazenamento | C9: HD 1TB SATA III | D9: Seagate | E9: Barracuda ST1000DM010 | F9: HD interno 3.5'' 7200RPM 64MB cache | G9: UN | H9: 15 | I9: 5 | J9: 25 | K9: 179 | L9: 299.9 | M9: =IFERROR((L9-K9)/K9,0) -> 0.67541899 | N9: =H9*K9 -> 2685 | O9: Seagate Distribuidor BR | P9: A1-08 | Q9: 28/08/2026 | R9: =IF(H9<=0,"SEM ESTOQUE",IF(H9<=I9,"ESTOQUE BAIXO","OK")) -> OK | S9: https://exemplo.com/imagens/hd-seagate-barracuda-1tb.jpg
A10: EST-005 | B10: Armazenamento | C10: HD 2TB SATA III | D10: Western Digital | E10: WD Blue WD20EZBX | F10: HD interno 3.5'' 7200RPM 256MB cache | G10: UN | H10: 7 | I10: 3 | J10: 15 | K10: 299 | L10: 459.9 | M10: =IFERROR((L10-K10)/K10,0) -> 0.53812709 | N10: =H10*K10 -> 2093 | O10: Western Digital Brasil | P10: A1-09 | Q10: 28/08/2026 | R10: =IF(H10<=0,"SEM ESTOQUE",IF(H10<=I10,"ESTOQUE BAIXO","OK")) -> OK | S10: https://exemplo.com/imagens/hd-wd-blue-2tb.jpg
A11: EST-006 | B11: Memória RAM | C11: Memória DDR4 8GB 2666MHz | D11: Kingston | E11: KVR26N19S8/8 | F11: Pente de memória DDR4 Non-ECC | G11: UN | H11: 22 | I11: 6 | J11: 30 | K11: 99 | L11: 179.9 | M11: =IFERROR((L11-K11)/K11,0) -> 0.81717172 | N11: =H11*K11 -> 2178 | O11: Kabum Distribuidora | P11: A2-01 | Q11: 05/09/2026 | R11: =IF(H11<=0,"SEM ESTOQUE",IF(H11<=I11,"ESTOQUE BAIXO","OK")) -> OK | S11: https://exemplo.com/imagens/ram-kingston-ddr4-8gb.jpg
A12: EST-007 | B12: Memória RAM | C12: Memória DDR4 16GB 3200MHz | D12: HyperX | E12: Fury HX432C16FB/16 | F12: Pente de memória DDR4 Non-ECC | G12: UN | H12: 14 | I12: 4 | J12: 20 | K12: 189 | L12: 329.9 | M12: =IFERROR((L12-K12)/K12,0) -> 0.74550265 | N12: =H12*K12 -> 2646 | O12: HyperX Brasil | P12: A2-02 | Q12: 05/09/2026 | R12: =IF(H12<=0,"SEM ESTOQUE",IF(H12<=I12,"ESTOQUE BAIXO","OK")) -> OK | S12: https://exemplo.com/imagens/ram-hyperx-fury-16gb.jpg
A13: EST-008 | B13: Memória RAM | C13: Memória DDR3 4GB 1600MHz | D13: Kingston | E13: KVR16N11S8/4 | F13: Pente de memória DDR3 Non-ECC — notebooks antigos | G13: UN | H13: 10 | I13: 3 | J13: 15 | K13: 69 | L13: 119.9 | M13: =IFERROR((L13-K13)/K13,0) -> 0.73768116 | N13: =H13*K13 -> 690 | O13: Kabum Distribuidora | P13: A2-05 | Q13: 15/08/2026 | R13: =IF(H13<=0,"SEM ESTOQUE",IF(H13<=I13,"ESTOQUE BAIXO","OK")) -> OK | S13: https://exemplo.com/imagens/ram-kingston-ddr3-4gb.jpg | T13: Linha em baixa, estoque residual
A14: EST-009 | B14: Memória RAM | C14: Memória Notebook DDR4 8GB SODIMM | D14: Crucial | E14: CT8G4SFS8266 | F14: Pente SODIMM para notebooks | G14: UN | H14: 11 | I14: 4 | J14: 18 | K14: 109 | L14: 189.9 | M14: =IFERROR((L14-K14)/K14,0) -> 0.74220183 | N14: =H14*K14 -> 1199 | O14: Crucial Memory BR | P14: A2-08 | Q14: 12/09/2026 | R14: =IF(H14<=0,"SEM ESTOQUE",IF(H14<=I14,"ESTOQUE BAIXO","OK")) -> OK | S14: https://exemplo.com/imagens/ram-crucial-sodimm-8gb.jpg
A15: EST-010 | B15: Fontes | C15: Fonte ATX 500W Real | D15: Corsair | E15: CV500 | F15: Fonte ATX 80 Plus Bronze, 500W reais | G15: UN | H15: 8 | I15: 3 | J15: 12 | K15: 229 | L15: 379.9 | M15: =IFERROR((L15-K15)/K15,0) -> 0.65895197 | N15: =H15*K15 -> 1832 | O15: Corsair Brasil | P15: A3-01 | Q15: 20/09/2026 | R15: =IF(H15<=0,"SEM ESTOQUE",IF(H15<=I15,"ESTOQUE BAIXO","OK")) -> OK | S15: https://exemplo.com/imagens/fonte-corsair-cv500.jpg
A16: EST-011 | B16: Fontes | C16: Fonte ATX 750W Real | D16: Corsair | E16: RM750x | F16: Fonte ATX 80 Plus Gold, modular, 750W reais | G16: UN | H16: 4 | I16: 2 | J16: 10 | K16: 549 | L16: 899.9 | M16: =IFERROR((L16-K16)/K16,0) -> 0.63916211 | N16: =H16*K16 -> 2196 | O16: Corsair Brasil | P16: A3-02 | Q16: 20/09/2026 | R16: =IF(H16<=0,"SEM ESTOQUE",IF(H16<=I16,"ESTOQUE BAIXO","OK")) -> OK | S16: https://exemplo.com/imagens/fonte-corsair-rm750x.jpg
A17: EST-012 | B17: Fontes | C17: Carregador Notebook 65W Universal | D17: MultiLaser | E17: CB122 | F17: Fonte universal com 8 plugues intercambiáveis | G17: UN | H17: 16 | I17: 5 | J17: 25 | K17: 59 | L17: 99.9 | M17: =IFERROR((L17-K17)/K17,0) -> 0.69322034 | N17: =H17*K17 -> 944 | O17: MultiLaser Distribuição | P17: A3-05 | Q17: 08/09/2026 | R17: =IF(H17<=0,"SEM ESTOQUE",IF(H17<=I17,"ESTOQUE BAIXO","OK")) -> OK | S17: https://exemplo.com/imagens/carregador-multilaser-65w.jpg
A18: EST-013 | B18: Bateria | C18: Bateria Notebook Dell Inspiron 15 | D18: Dell | E18: Compatível 3451/3551 (11.1V 4400mAh) | F18: Bateria compatível, 6 células | G18: UN | H18: 6 | I18: 3 | J18: 12 | K18: 139 | L18: 249.9 | M18: =IFERROR((L18-K18)/K18,0) -> 0.79784173 | N18: =H18*K18 -> 834 | O18: PeçasNote Distribuidora | P18: A4-01 | Q18: 01/09/2026 | R18: =IF(H18<=0,"SEM ESTOQUE",IF(H18<=I18,"ESTOQUE BAIXO","OK")) -> OK | S18: https://exemplo.com/imagens/bateria-dell-inspiron15.jpg
A19: EST-014 | B19: Bateria | C19: Bateria Notebook Lenovo Ideapad 320 | D19: Lenovo | E19: Compatível L16L6PB1 (7.5V 4050mAh) | F19: Bateria compatível, 2 células | G19: UN | H19: 5 | I19: 3 | J19: 12 | K19: 129 | L19: 229.9 | M19: =IFERROR((L19-K19)/K19,0) -> 0.78217054 | N19: =H19*K19 -> 645 | O19: PeçasNote Distribuidora | P19: A4-02 | Q19: 01/09/2026 | R19: =IF(H19<=0,"SEM ESTOQUE",IF(H19<=I19,"ESTOQUE BAIXO","OK")) -> OK | S19: https://exemplo.com/imagens/bateria-lenovo-ideapad320.jpg
A20: EST-015 | B20: Placa-mãe | C20: Placa-mãe LGA 1200 H510M | D20: ASUS | E20: PRIME H510M-E | F20: Placa-mãe mATX, DDR4, suporte Intel 10ª/11ª geração | G20: UN | H20: 3 | I20: 2 | J20: 8 | K20: 429 | L20: 699.9 | M20: =IFERROR((L20-K20)/K20,0) -> 0.63146853 | N20: =H20*K20 -> 1287 | O20: ASUS Brasil Distribuidor | P20: A5-01 | Q20: 18/09/2026 | R20: =IF(H20<=0,"SEM ESTOQUE",IF(H20<=I20,"ESTOQUE BAIXO","OK")) -> OK | S20: https://exemplo.com/imagens/placa-mae-asus-h510m.jpg | T20: Item de alto valor — conferir antes de vender
A21: EST-016 | B21: Placa-mãe | C21: Placa-mãe AM4 B450M | D21: Gigabyte | E21: B450M DS3H | F21: Placa-mãe mATX, DDR4, suporte AMD Ryzen | G21: UN | H21: 5 | I21: 2 | J21: 8 | K21: 459 | L21: 749.9 | M21: =IFERROR((L21-K21)/K21,0) -> 0.63376906 | N21: =H21*K21 -> 2295 | O21: Gigabyte Brasil Distribuidor | P21: A5-02 | Q21: 18/09/2026 | R21: =IF(H21<=0,"SEM ESTOQUE",IF(H21<=I21,"ESTOQUE BAIXO","OK")) -> OK | S21: https://exemplo.com/imagens/placa-mae-gigabyte-b450m.jpg
A22: EST-017 | B22: Processador | C22: Processador Intel Core i3-10100F | D22: Intel | E22: i3-10100F 3.6GHz | F22: 4 núcleos / 8 threads, sem vídeo integrado | G22: UN | H22: 4 | I22: 2 | J22: 10 | K22: 489 | L22: 799.9 | M22: =IFERROR((L22-K22)/K22,0) -> 0.63578732 | N22: =H22*K22 -> 1956 | O22: Intel Distribuidor BR | P22: A5-05 | Q22: 22/09/2026 | R22: =IF(H22<=0,"SEM ESTOQUE",IF(H22<=I22,"ESTOQUE BAIXO","OK")) -> OK | S22: https://exemplo.com/imagens/cpu-intel-i3-10100f.jpg
A23: EST-018 | B23: Processador | C23: Processador AMD Ryzen 5 5600 | D23: AMD | E23: Ryzen 5 5600 3.5GHz | F23: 6 núcleos / 12 threads | G23: UN | H23: 3 | I23: 2 | J23: 8 | K23: 799 | L23: 1249.9 | M23: =IFERROR((L23-K23)/K23,0) -> 0.56433041 | N23: =H23*K23 -> 2397 | O23: AMD Distribuidor BR | P23: A5-06 | Q23: 22/09/2026 | R23: =IF(H23<=0,"SEM ESTOQUE",IF(H23<=I23,"ESTOQUE BAIXO","OK")) -> OK | S23: https://exemplo.com/imagens/cpu-amd-ryzen5-5600.jpg
A24: EST-019 | B24: Refrigeração | C24: Cooler para Processador Gamer | D24: Cooler Master | E24: Hyper 212 Black Edition | F24: Cooler a ar com dissipador de calor duplo | G24: UN | H24: 9 | I24: 3 | J24: 15 | K24: 139 | L24: 229.9 | M24: =IFERROR((L24-K24)/K24,0) -> 0.65395683 | N24: =H24*K24 -> 1251 | O24: Cooler Master Brasil | P24: A6-01 | Q24: 14/09/2026 | R24: =IF(H24<=0,"SEM ESTOQUE",IF(H24<=I24,"ESTOQUE BAIXO","OK")) -> OK | S24: https://exemplo.com/imagens/cooler-master-hyper212.jpg
A25: EST-020 | B25: Refrigeração | C25: Cooler Cooler Box Padrão (box) | D25: Intel/AMD | E25: Cooler Box Padrão | F25: Cooler original que acompanha o processador | G25: UN | H25: 20 | I25: 6 | J25: 30 | K25: 25 | L25: 49.9 | M25: =IFERROR((L25-K25)/K25,0) -> 0.996 | N25: =H25*K25 -> 500 | O25: Estoque de reaproveitamento | P25: A6-03 | Q25: 01/09/2026 | R25: =IF(H25<=0,"SEM ESTOQUE",IF(H25<=I25,"ESTOQUE BAIXO","OK")) -> OK | S25: https://exemplo.com/imagens/cooler-box-padrao.jpg
A26: EST-021 | B26: Refrigeração | C26: Pasta Térmica 4g | D26: Implastec | E26: MX-4 Compatível | F26: Pasta térmica de alta performance para CPU/GPU | G26: UN | H26: 30 | I26: 10 | J26: 50 | K26: 12 | L26: 24.9 | M26: =IFERROR((L26-K26)/K26,0) -> 1.075 | N26: =H26*K26 -> 360 | O26: Implastec Distribuidora | P26: A6-05 | Q26: 25/09/2026 | R26: =IF(H26<=0,"SEM ESTOQUE",IF(H26<=I26,"ESTOQUE BAIXO","OK")) -> OK | S26: https://exemplo.com/imagens/pasta-termica-4g.jpg
A27: EST-022 | B27: Periféricos | C27: Teclado USB ABNT2 | D27: MultiLaser | E27: TC254 | F27: Teclado padrão ABNT2 com fio, USB | G27: UN | H27: 17 | I27: 5 | J27: 25 | K27: 29 | L27: 59.9 | M27: =IFERROR((L27-K27)/K27,0) -> 1.0655172 | N27: =H27*K27 -> 493 | O27: MultiLaser Distribuição | P27: A7-01 | Q27: 06/09/2026 | R27: =IF(H27<=0,"SEM ESTOQUE",IF(H27<=I27,"ESTOQUE BAIXO","OK")) -> OK | S27: https://exemplo.com/imagens/teclado-multilaser-tc254.jpg
A28: EST-023 | B28: Periféricos | C28: Mouse Óptico USB | D28: Logitech | E28: B100 | F28: Mouse óptico com fio, 800 DPI | G28: UN | H28: 25 | I28: 8 | J28: 35 | K28: 24 | L28: 49.9 | M28: =IFERROR((L28-K28)/K28,0) -> 1.0791667 | N28: =H28*K28 -> 600 | O28: Logitech Brasil | P28: A7-02 | Q28: 06/09/2026 | R28: =IF(H28<=0,"SEM ESTOQUE",IF(H28<=I28,"ESTOQUE BAIXO","OK")) -> OK | S28: https://exemplo.com/imagens/mouse-logitech-b100.jpg
A29: EST-024 | B29: Periféricos | C29: Fonte de Notebook Universal 90W | D29: MultiLaser | E29: CB123 | F29: Fonte chaveada universal com múltiplos plugues | G29: UN | H29: 10 | I29: 4 | J29: 18 | K29: 69 | L29: 119.9 | M29: =IFERROR((L29-K29)/K29,0) -> 0.73768116 | N29: =H29*K29 -> 690 | O29: MultiLaser Distribuição | P29: A7-05 | Q29: 06/09/2026 | R29: =IF(H29<=0,"SEM ESTOQUE",IF(H29<=I29,"ESTOQUE BAIXO","OK")) -> OK | S29: https://exemplo.com/imagens/fonte-notebook-90w.jpg
A30: EST-025 | B30: Tela / Display | C30: Tela Notebook 15.6'' LED HD | D30: Genérica (AUO/BOE) | E30: 15.6'' 1366x768 30 pinos | F30: Tela LED para notebooks diversos | G30: UN | H30: 4 | I30: 2 | J30: 10 | K30: 219 | L30: 379.9 | M30: =IFERROR((L30-K30)/K30,0) -> 0.7347032 | N30: =H30*K30 -> 876 | O30: TelaNote Distribuidora | P30: A8-01 | Q30: 19/09/2026 | R30: =IF(H30<=0,"SEM ESTOQUE",IF(H30<=I30,"ESTOQUE BAIXO","OK")) -> OK | S30: https://exemplo.com/imagens/tela-notebook-156-hd.jpg | T30: Confirmar modelo compatível antes da venda
A31: EST-026 | B31: Tela / Display | C31: Tela Notebook 14'' LED HD Slim | D31: Genérica (AUO/BOE) | E31: 14'' 1366x768 30 pinos Slim | F31: Tela LED slim para notebooks ultrafinos | G31: UN | H31: 3 | I31: 2 | J31: 8 | K31: 229 | L31: 399.9 | M31: =IFERROR((L31-K31)/K31,0) -> 0.74628821 | N31: =H31*K31 -> 687 | O31: TelaNote Distribuidora | P31: A8-02 | Q31: 19/09/2026 | R31: =IF(H31<=0,"SEM ESTOQUE",IF(H31<=I31,"ESTOQUE BAIXO","OK")) -> OK | S31: https://exemplo.com/imagens/tela-notebook-14-slim.jpg
A32: EST-027 | B32: Cabos e Conectores | C32: Cabo SATA de Dados | D32: Genérico | E32: SATA III 50cm | F32: Cabo de dados SATA III para HD/SSD | G32: UN | H32: 40 | I32: 10 | J32: 60 | K32: 6 | L32: 14.9 | M32: =IFERROR((L32-K32)/K32,0) -> 1.4833333 | N32: =H32*K32 -> 240 | O32: Estoque Avulso BR | P32: A9-01 | Q32: 02/09/2026 | R32: =IF(H32<=0,"SEM ESTOQUE",IF(H32<=I32,"ESTOQUE BAIXO","OK")) -> OK | S32: https://exemplo.com/imagens/cabo-sata-dados.jpg
A33: EST-028 | B33: Cabos e Conectores | C33: Cabo de Força PC (3 pinos) | D33: Genérico | E33: Padrão NBR 14136 | F33: Cabo de alimentação para fonte ATX | G33: UN | H33: 35 | I33: 10 | J33: 50 | K33: 8 | L33: 17.9 | M33: =IFERROR((L33-K33)/K33,0) -> 1.2375 | N33: =H33*K33 -> 280 | O33: Estoque Avulso BR | P33: A9-02 | Q33: 02/09/2026 | R33: =IF(H33<=0,"SEM ESTOQUE",IF(H33<=I33,"ESTOQUE BAIXO","OK")) -> OK | S33: https://exemplo.com/imagens/cabo-forca-pc.jpg
A34: EST-029 | B34: Cabos e Conectores | C34: Cabo HDMI 1.8m | D34: Genérico | E34: HDMI 2.0 Full HD/4K | F34: Cabo de vídeo HDMI macho-macho | G34: UN | H34: 28 | I34: 8 | J34: 40 | K34: 14 | L34: 29.9 | M34: =IFERROR((L34-K34)/K34,0) -> 1.1357143 | N34: =H34*K34 -> 392 | O34: Estoque Avulso BR | P34: A9-04 | Q34: 02/09/2026 | R34: =IF(H34<=0,"SEM ESTOQUE",IF(H34<=I34,"ESTOQUE BAIXO","OK")) -> OK | S34: https://exemplo.com/imagens/cabo-hdmi-18m.jpg
A35: EST-030 | B35: Limpeza e Manutenção | C35: Ar Comprimido Spray 300ml | D35: Implastec | E35: Jato de Ar Seco | F35: Spray de ar comprimido para limpeza de componentes | G35: UN | H35: 14 | I35: 5 | J35: 25 | K35: 22 | L35: 39.9 | M35: =IFERROR((L35-K35)/K35,0) -> 0.81363636 | N35: =H35*K35 -> 308 | O35: Implastec Distribuidora | P35: A10-01 | Q35: 25/09/2026 | R35: =IF(H35<=0,"SEM ESTOQUE",IF(H35<=I35,"ESTOQUE BAIXO","OK")) -> OK | S35: https://exemplo.com/imagens/ar-comprimido-spray.jpg
A36: EST-031 | B36: Limpeza e Manutenção | C36: Álcool Isopropílico 99% 100ml | D36: Implastec | E36: Isopropílico Eletrônico | F36: Álcool para limpeza de placas e contatos eletrônicos | G36: UN | H36: 12 | I36: 4 | J36: 20 | K36: 18 | L36: 32.9 | M36: =IFERROR((L36-K36)/K36,0) -> 0.82777778 | N36: =H36*K36 -> 216 | O36: Implastec Distribuidora | P36: A10-02 | Q36: 25/09/2026 | R36: =IF(H36<=0,"SEM ESTOQUE",IF(H36<=I36,"ESTOQUE BAIXO","OK")) -> OK | S36: https://exemplo.com/imagens/alcool-isopropilico-100ml.jpg
A37: EST-032 | B37: Ferramentas | C37: Kit Chaves de Precisão (32 peças) | D37: Vonder | E37: Kit Eletrônica 32pç | F37: Kit de chaves Phillips/fenda para manutenção eletrônica | G37: UN | H37: 6 | I37: 2 | J37: 10 | K37: 45 | L37: 79.9 | M37: =IFERROR((L37-K37)/K37,0) -> 0.77555556 | N37: =H37*K37 -> 270 | O37: Vonder Ferramentas | P37: B1-01 | Q37: 11/09/2026 | R37: =IF(H37<=0,"SEM ESTOQUE",IF(H37<=I37,"ESTOQUE BAIXO","OK")) -> OK | S37: https://exemplo.com/imagens/kit-chaves-precisao.jpg | T37: Uso interno da oficina, controlar saída
A38: EST-033 | B38: Ferramentas | C38: Pulseira Antiestática | D38: Vonder | E38: Antiestática com fio terra | F38: Pulseira de segurança para manuseio de componentes | G38: UN | H38: 8 | I38: 2 | J38: 10 | K38: 19 | L38: 34.9 | M38: =IFERROR((L38-K38)/K38,0) -> 0.83684211 | N38: =H38*K38 -> 152 | O38: Vonder Ferramentas | P38: B1-02 | Q38: 11/09/2026 | R38: =IF(H38<=0,"SEM ESTOQUE",IF(H38<=I38,"ESTOQUE BAIXO","OK")) -> OK | S38: https://exemplo.com/imagens/pulseira-antiestatica.jpg | T38: Uso interno da oficina
A39: EST-034 | B39: Armazenamento | C39: Pendrive 32GB USB 3.0 | D39: SanDisk | E39: Ultra Flair 32GB | F39: Pendrive USB 3.0 alta velocidade | G39: UN | H39: 2 | I39: 5 | J39: 25 | K39: 29 | L39: 54.9 | M39: =IFERROR((L39-K39)/K39,0) -> 0.89310345 | N39: =H39*K39 -> 58 | O39: SanDisk Brasil | P39: A1-11 | Q39: 30/09/2026 | R39: =IF(H39<=0,"SEM ESTOQUE",IF(H39<=I39,"ESTOQUE BAIXO","OK")) -> ESTOQUE BAIXO | S39: https://exemplo.com/imagens/pendrive-sandisk-32gb.jpg | T39: Reabastecer — abaixo do mínimo
A40: EST-035 | B40: Rede | C40: Adaptador Wi-Fi USB AC600 | D40: TP-Link | E40: Archer T2U Nano | F40: Adaptador de rede sem fio USB dual band | G40: UN | H40: 0 | I40: 3 | J40: 15 | K40: 49 | L40: 89.9 | M40: =IFERROR((L40-K40)/K40,0) -> 0.83469388 | N40: =H40*K40 -> 0 | O40: TP-Link Brasil | P40: A11-01 | Q40: 20/08/2026 | R40: =IF(H40<=0,"SEM ESTOQUE",IF(H40<=I40,"ESTOQUE BAIXO","OK")) -> SEM ESTOQUE | S40: https://exemplo.com/imagens/adaptador-wifi-tplink.jpg | T40: Em falta — pedido de reposição enviado
C42: TOTAIS | H42: =SUM(H6:H40) -> 435 | N42: =SUM(N6:N40) -> 38449

Sheet Resumo
A1: RESUMO DO ESTOQUE
A2: Todos os valores abaixo são calculados automaticamente a partir da aba 'Estoque'.
A4: Total de itens cadastrados | B4: =COUNTA(Estoque!A6:A40) -> 35
A5: Quantidade total em estoque (unidades) | B5: =SUM(Estoque!H6:H40) -> 435
A6: Valor total do estoque (custo) (R$) | B6: =SUM(Estoque!N6:N40) -> 38449
A7: Valor total do estoque (venda) (R$) | B7: =SUMPRODUCT(Estoque!H6:H40,Estoque!L6:L40) -> 66292.5
A8: Itens com status OK | B8: =COUNTIF(Estoque!R6:R40,"OK") -> 33
A9: Itens com estoque baixo | B9: =COUNTIF(Estoque!R6:R40,"ESTOQUE BAIXO") -> 1
A10: Itens sem estoque | B10: =COUNTIF(Estoque!R6:R40,"SEM ESTOQUE") -> 1
A11: Preço médio de venda (R$) | B11: =AVERAGE(Estoque!L6:L40) -> 268.78571
A12: Margem média (%) | B12: =AVERAGE(Estoque!M6:M40) -> 0.81421413
A14: Itens por categoria
A15: Categoria | B15: Qtd. de itens
A16: Armazenamento | B16: =COUNTIF(Estoque!B$6:B$40,A16) -> 6
A17: Bateria | B17: =COUNTIF(Estoque!B$6:B$40,A17) -> 2
A18: Cabos e Conectores | B18: =COUNTIF(Estoque!B$6:B$40,A18) -> 3
A19: Ferramentas | B19: =COUNTIF(Estoque!B$6:B$40,A19) -> 2
A20: Fontes | B20: =COUNTIF(Estoque!B$6:B$40,A20) -> 3
A21: Limpeza e Manutenção | B21: =COUNTIF(Estoque!B$6:B$40,A21) -> 2
A22: Memória RAM | B22: =COUNTIF(Estoque!B$6:B$40,A22) -> 4
A23: Periféricos | B23: =COUNTIF(Estoque!B$6:B$40,A23) -> 3
A24: Placa-mãe | B24: =COUNTIF(Estoque!B$6:B$40,A24) -> 2
A25: Processador | B25: =COUNTIF(Estoque!B$6:B$40,A25) -> 2
A26: Rede | B26: =COUNTIF(Estoque!B$6:B$40,A26) -> 1
A27: Refrigeração | B27: =COUNTIF(Estoque!B$6:B$40,A27) -> 3
A28: Tela / Display | B28: =COUNTIF(Estoque!B$6:B$40,A28) -> 2
